{
  "templates": {
    "type": "JSON",
    "content": [
      {
        "id": "4752W9",
        "Flight": "B61168",
        "PickupDate": "2026-01-18",
        "PickupTime": "13:05",
        "HotelName": "Royalton Bavaro Resort & Spa",
        "HotelNumber": 13689
      },
      {
        "id": "8CR333",
        "Flight": "DM1000",
        "PickupDate": "2026-01-18",
        "PickupTime": "09:30",
        "HotelName": "Royalton Bavaro Resort & Spa",
        "HotelNumber": 13689
      },
      {
        "id": "9118KX",
        "Flight": "DL1844",
        "PickupDate": "2026-01-18",
        "PickupTime": "12:30",
        "HotelName": "Royalton Bavaro Resort & Spa",
        "HotelNumber": 13689
      },
      {
        "id": "BH7H2C",
        "Flight": "DL1835",
        "PickupDate": "2026-01-18",
        "PickupTime": "12:20",
        "HotelName": "Royalton Bavaro Resort & Spa",
        "HotelNumber": 13689
      },
      {
        "id": "LMKK1J",
        "Flight": "AA1899",
        "PickupDate": "2026-01-18",
        "PickupTime": "11:25",
        "HotelName": "Royalton Bavaro Resort & Spa",
        "HotelNumber": 13689
      },
      {
        "id": "RR311B",
        "Flight": "AA1899",
        "PickupDate": "2026-01-18",
        "PickupTime": "12:00",
        "HotelName": "Royalton Bavaro Resort & Spa",
        "HotelNumber": 13689
      },
      {
        "id": "SHXRSM",
        "Flight": "DL1836",
        "PickupDate": "2026-01-18",
        "PickupTime": "12:40",
        "HotelName": "Royalton Bavaro Resort & Spa",
        "HotelNumber": 13689
      },
      {
        "id": "Y3KK2K",
        "Flight": "WS2103",
        "PickupDate": "2026-01-18",
        "PickupTime": "12:40",
        "HotelName": "Royalton Bavaro Resort & Spa",
        "HotelNumber": 13689
      }
    ],
    "source": {
      "data_source": "Google Sheets (Private)",
      "update_frequency": "Automated"
    }
  }
}